pyeasy_crc/__init__.py
pyeasy_crc/source/crc8.py
pyeasy_crc/source/algorithms/Algorithm.py
pyeasy_crc/source/algorithms/Algorithms.py
pyeasy_crc/source/algorithms/cdma2000.py
pyeasy_crc/source/algorithms/ebu.py
pyeasy_crc/source/algorithms/i_code.py
pyeasy_crc/source/algorithms/itu.py
pyeasy_crc/source/algorithms/maxim.py
pyeasy_crc/source/algorithms/rohc.py
pyeasy_crc/source/types/AlgorithmKeys.py
pyeasy_crc-0.0.5.dist-info/METADATA
pyeasy_crc-0.0.5.dist-info/WHEEL
pyeasy_crc-0.0.5.dist-info/licenses/LICENSE
pyeasy_crc-0.0.5.dist-info/RECORD
